{
  "countries_ccn3": "762",
  "cities": [
    {
      "name": "Dushanbe",
      "population": 679400,
      "translations": {
        "aze": "Duşənbə",
        "bel": "Душанбэ",
        "eng": "Dushanbe",
        "hye": "Դուշանբե",
        "hin": "दुशान्बे",
        "ind": "Dushanbe",
        "kat": "დუშანბე",
        "kaz": "Дүшәнбе",
        "kir": "Душанбе",
        "msa": "Dushanbe",
        "por": "Duchambe",
        "rus": "Душанбе",
        "spa": "Dusambé",
        "tgk": "Душанбе",
        "uzb": "Dushanbe",
        "ukr": "Душанбе"
      }
    },
    {
      "name": "Isfara",
      "population": 274000,
      "translations": {
        "aze": "İsfəra",
        "bel": "Ісфара",
        "eng": "Isfara",
        "hye": "Իսֆարա",
        "hin": "इस्फ़ारा",
        "ind": "Isfara",
        "kat": "ისფარა",
        "kaz": "Исфара",
        "kir": "Исфара",
        "msa": "Isfara",
        "por": "Isfara",
        "rus": "Исфара",
        "spa": "Isfara",
        "tgk": "Исфара",
        "uzb": "Isfara",
        "ukr": "Ісфара"
      }
    },
    {
      "name": "Istaravshan",
      "population": 273500,
      "translations": {
        "aze": "İstaravşan",
        "bel": "Істараўшан",
        "eng": "Istaravshan",
        "hye": "Իստարավշան",
        "hin": "इस्तरावशान",
        "ind": "Istaravshan",
        "kat": "ისტარავშანი",
        "kaz": "Истаравшан",
        "kir": "Истаравшан",
        "msa": "Istaravshan",
        "por": "Istaravshan",
        "rus": "Истаравшан",
        "spa": "Istaravshan",
        "tgk": "Истаравшан",
        "uzb": "Istaravshan",
        "ukr": "Істаравшан"
      }
    },
    {
      "name": "Kulob",
      "population": 214700,
      "translations": {
        "aze": "Küləb",
        "bel": "Куляб",
        "eng": "Kulob",
        "hye": "Կուլյաբ",
        "hin": "कुलोब",
        "ind": "Kulob",
        "kat": "კულობი",
        "kaz": "Күләп",
        "kir": "Куляб",
        "msa": "Kulob",
        "por": "Kulob",
        "rus": "Куляб",
        "spa": "Kulob",
        "tgk": "Кулоб",
        "uzb": "Kulob",
        "ukr": "Куляб"
      }
    },
    {
      "name": "Konibodom",
      "population": 211100,
      "translations": {
        "aze": "Konibodom",
        "bel": "Канібадам",
        "eng": "Konibodom",
        "hye": "Կոնիբոդոմ",
        "hin": "कोनिबोदोम",
        "ind": "Konibodom",
        "kat": "კონიბოდომი",
        "kaz": "Қонибодом",
        "kir": "Конибодом",
        "msa": "Konibodom",
        "por": "Konibodom",
        "rus": "Конибодом",
        "spa": "Konibodom",
        "tgk": "Қунибодом",
        "uzb": "Konibodom",
        "ukr": "Конибодом"
      }
    },
    {
      "name": "Khujand",
      "population": 191000,
      "translations": {
        "aze": "Xucənd",
        "bel": "Худжанд",
        "eng": "Khujand",
        "hye": "Խուջանդ",
        "hin": "खुजंद",
        "ind": "Khujand",
        "kat": "ხუჯანდი",
        "kaz": "Худжанд",
        "kir": "Худжанд",
        "msa": "Khujand",
        "por": "Khujand",
        "rus": "Худжанд",
        "spa": "Khujand",
        "tgk": "Хуҷанд",
        "uzb": "Xujand",
        "ukr": "Худжанд"
      }
    },
    {
      "name": "Bokhtar",
      "population": 110800,
      "translations": {
        "aze": "Böxtər",
        "bel": "Бахтар",
        "eng": "Bokhtar",
        "hye": "Բոխտար",
        "hin": "बोख्तर",
        "ind": "Bokhtar",
        "kat": "ბოხტარი",
        "kaz": "Бохтар",
        "kir": "Бохтар",
        "msa": "Bokhtar",
        "por": "Bokhtar",
        "rus": "Бохтар",
        "spa": "Bokhtar",
        "tgk": "Бохтар",
        "uzb": "Boxtar",
        "ukr": "Бохтар"
      }
    },
    {
      "name": "Qayroqqum",
      "population": 49200,
      "translations": {
        "aze": "Qayroqqım",
        "bel": "Кайраккум",
        "eng": "Qayroqqum",
        "hye": "Քայրոքքում",
        "hin": "क़ैरोक़्क़ुम",
        "ind": "Qayroqqum",
        "kat": "ყაიროყუმი",
        "kaz": "Қайраққұм",
        "kir": "Кайраккум",
        "msa": "Qayroqqum",
        "por": "Qayroqqum",
        "rus": "Кайраккум",
        "spa": "Qayroqqum",
        "tgk": "Қайраққум",
        "uzb": "Qayroqqum",
        "ukr": "Кайраккум"
      }
    },
    {
      "name": "Vahdat",
      "population": 45693,
      "translations": {
        "aze": "Vəhdət",
        "bel": "Вахдат",
        "eng": "Vahdat",
        "hye": "Վահդատ",
        "hin": "वहदत",
        "ind": "Vahdat",
        "kat": "ვაჰდათი",
        "kaz": "Вахдат",
        "kir": "Вахдат",
        "msa": "Vahdat",
        "por": "Vahdat",
        "rus": "Вахдат",
        "spa": "Vahdat",
        "tgk": "Ваҳдат",
        "uzb": "Vahdat",
        "ukr": "Вахдат"
      }
    },
    {
      "name": "Tursunzoda",
      "population": 37000,
      "translations": {
        "aze": "Tursunzadə",
        "bel": "Турсунзадэ",
        "eng": "Tursunzoda",
        "hye": "Թուրսունզոդա",
        "hin": "तुर्सुनज़ोदा",
        "ind": "Tursunzoda",
        "kat": "თურსუნზოდა",
        "kaz": "Түрсүнзада",
        "kir": "Турсунзада",
        "msa": "Tursunzoda",
        "por": "Tursunzoda",
        "rus": "Турсунзаде",
        "spa": "Tursunzoda",
        "tgk": "Турсунзода",
        "uzb": "Tursunzoda",
        "ukr": "Турсунзаде"
      }
    },
    {
      "name": "Buston",
      "population": 36900,
      "translations": {
        "aze": "Buston",
        "bel": "Бустон",
        "eng": "Buston",
        "hye": "Բուստոն",
        "hin": "बुस्तोन",
        "ind": "Buston",
        "kat": "ბუსტონი",
        "kaz": "Бүстон",
        "kir": "Бустон",
        "msa": "Buston",
        "por": "Buston",
        "rus": "Бустон",
        "spa": "Buston",
        "tgk": "Бустон",
        "uzb": "Buston",
        "ukr": "Бустон"
      }
    },
    {
      "name": "Panjakent",
      "population": 35085,
      "translations": {
        "aze": "Pəncəkənt",
        "bel": "Панджакент",
        "eng": "Panjakent",
        "hye": "Պանջակենտ",
        "hin": "पंजाकेंत",
        "ind": "Panjakent",
        "kat": "პანჯაკენტი",
        "kaz": "Пенджикент",
        "kir": "Пенджикент",
        "msa": "Panjakent",
        "por": "Panjakent",
        "rus": "Пенджикент",
        "spa": "Panjakent",
        "tgk": "Панҷакент",
        "uzb": "Panjakent",
        "ukr": "Пенджикент"
      }
    },
    {
      "name": "Khorugh",
      "population": 30500,
      "translations": {
        "aze": "Xoruğ",
        "bel": "Харуг",
        "eng": "Khorugh",
        "hye": "Խորուղ",
        "hin": "ख़ोरुग",
        "ind": "Khorugh",
        "kat": "ხორუღი",
        "kaz": "Хоруғ",
        "kir": "Хоруг",
        "msa": "Khorugh",
        "por": "Khorugh",
        "rus": "Хорог",
        "spa": "Khorugh",
        "tgk": "Хоруғ",
        "uzb": "Xorug'",
        "ukr": "Хорог"
      }
    },
    {
      "name": "Ishqoshim",
      "population": 26000,
      "translations": {
        "aze": "İşqoşim",
        "bel": "Ішкошым",
        "eng": "Ishqoshim",
        "hye": "Իշքոշիմ",
        "hin": "इश्कोशिम",
        "ind": "Ishqoshim",
        "kat": "იშყოშიმი",
        "kaz": "Ишқошим",
        "kir": "Ишкошим",
        "msa": "Ishqoshim",
        "por": "Ishqoshim",
        "rus": "Ишкошим",
        "spa": "Ishqoshim",
        "tgk": "Ишқошим",
        "uzb": "Ishqoshim",
        "ukr": "Ішкошим"
      }
    },
    {
      "name": "Hisor",
      "population": 23978,
      "translations": {
        "aze": "Hisor",
        "bel": "Гісор",
        "eng": "Hisor",
        "hye": "Հիսոր",
        "hin": "हिसोर",
        "ind": "Hisor",
        "kat": "ჰისორი",
        "kaz": "Һисор",
        "kir": "Һисор",
        "msa": "Hisor",
        "por": "Hisor",
        "rus": "Гиссар",
        "spa": "Hisor",
        "tgk": "Ҳисор",
        "uzb": "Hisor",
        "ukr": "Гісор"
      }
    },
    {
      "name": "Boshkengash",
      "population": 23696,
      "translations": {
        "aze": "Boşkəngəş",
        "bel": "Башкендэш",
        "eng": "Boshkengash",
        "hye": "Բոշկենգաշ",
        "hin": "बोशकेंगश",
        "ind": "Boshkengash",
        "kat": "ბოშკენგაში",
        "kaz": "Боскенгаш",
        "kir": "Боскенгаш",
        "msa": "Boshkengash",
        "por": "Boshkengash",
        "rus": "Бошкенгаш",
        "spa": "Boshkengash",
        "tgk": "Бошкенгаш",
        "uzb": "Boshkengash",
        "ukr": "Бошкенгаш"
      }
    },
    {
      "name": "Danghara",
      "population": 22824,
      "translations": {
        "aze": "Danğara",
        "bel": "Дангара",
        "eng": "Danghara",
        "hye": "Դանգարա",
        "hin": "दंघरा",
        "ind": "Danghara",
        "kat": "დანგარა",
        "kaz": "Данғара",
        "kir": "Дангара",
        "msa": "Danghara",
        "por": "Danghara",
        "rus": "Дангара",
        "spa": "Danghara",
        "tgk": "Данғара",
        "uzb": "Danghara",
        "ukr": "Дангара"
      }
    },
    {
      "name": "Moskovskiy",
      "population": 22100,
      "translations": {
        "aze": "Moskovski",
        "bel": "Маскоўскі",
        "eng": "Moskovskiy",
        "hye": "Մոսկովսկի",
        "hin": "मोस्कोव्स्की",
        "ind": "Moskovskiy",
        "kat": "მოსკოვსკი",
        "kaz": "Московский",
        "kir": "Московский",
        "msa": "Moskovskiy",
        "por": "Moskovskiy",
        "rus": "Московский",
        "spa": "Moskovskiy",
        "tgk": "Московский",
        "uzb": "Moskovskiy",
        "ukr": "Московський"
      }
    },
    {
      "name": "Hulbuk",
      "population": 21736,
      "translations": {
        "aze": "Hülbük",
        "bel": "Гульбук",
        "eng": "Hulbuk",
        "hye": "Հուլբուկ",
        "hin": "हुल्बुक",
        "ind": "Hulbuk",
        "kat": "ჰულბუკი",
        "kaz": "Ұлбұқ",
        "kir": "Үлбук",
        "msa": "Hulbuk",
        "por": "Hulbuk",
        "rus": "Гульбук",
        "spa": "Hulbuk",
        "tgk": "Ҳулбук",
        "uzb": "Hulbuk",
        "ukr": "Гульбук"
      }
    },
    {
      "name": "Farkhor",
      "population": 21736,
      "translations": {
        "aze": "Fərxor",
        "bel": "Фархор",
        "eng": "Farkhor",
        "hye": "Ֆարխոր",
        "hin": "फ़रख़ोर",
        "ind": "Farkhor",
        "kat": "ფარხორი",
        "kaz": "Фархор",
        "kir": "Фархор",
        "msa": "Farkhor",
        "por": "Farkhor",
        "rus": "Фархор",
        "spa": "Farkhor",
        "tgk": "Фархор",
        "uzb": "Farxor",
        "ukr": "Фархор"
      }
    },
    {
      "name": "Chubek",
      "population": 19563,
      "translations": {
        "aze": "Çubək",
        "bel": "Чубек",
        "eng": "Chubek",
        "hye": "Չուբեկ",
        "hin": "चुबेक",
        "ind": "Chubek",
        "kat": "ჩუბეკი",
        "kaz": "Шүбек",
        "kir": "Чүбөк",
        "msa": "Chubek",
        "por": "Chubek",
        "rus": "Чубек",
        "spa": "Chubek",
        "tgk": "Чубек",
        "uzb": "Chubek",
        "ukr": "Чубек"
      }
    },
    {
      "name": "Kolkhozobod",
      "population": 18476,
      "translations": {
        "aze": "Kolkhozabad",
        "bel": "Каўхбабад",
        "eng": "Kolkhozobod",
        "hye": "Կոլխոզաբադ",
        "hin": "कोल्खोज़ोबोद",
        "ind": "Kolkhozobod",
        "kat": "კოლხოზაბადი",
        "kaz": "Кеңес",
        "kir": "Кеңеш",
        "msa": "Kolkhozobod",
        "por": "Kolkhozobod",
        "rus": "Калхозабад",
        "spa": "Kolkhozobod",
        "tgk": "Калхозабод",
        "uzb": "Kolkhozobod",
        "ukr": "Калхозабад"
      }
    },
    {
      "name": "Norak",
      "population": 18122,
      "translations": {
        "aze": "Norak",
        "bel": "Нарака",
        "eng": "Norak",
        "hye": "Նորակ",
        "hin": "नोरक",
        "ind": "Norak",
        "kat": "ნორაკი",
        "kaz": "Норак",
        "kir": "Норак",
        "msa": "Norak",
        "por": "Norak",
        "rus": "Норак",
        "spa": "Norak",
        "tgk": "Норак",
        "uzb": "Norak",
        "ukr": "Норак"
      }
    },
    {
      "name": "Taboshar",
      "population": 17600,
      "translations": {
        "aze": "Taboşər",
        "bel": "Табошар",
        "eng": "Taboshar",
        "hye": "Տաբոշար",
        "hin": "तबोशर",
        "ind": "Taboshar",
        "kat": "ტაბოშარი",
        "kaz": "Табошар",
        "kir": "Табошар",
        "msa": "Taboshar",
        "por": "Taboshar",
        "rus": "Табошар",
        "spa": "Taboshar",
        "tgk": "Табошар",
        "uzb": "Taboshar",
        "ukr": "Табошар"
      }
    },
    {
      "name": "Yovon",
      "population": 17471,
      "translations": {
        "aze": "Yovon",
        "bel": "Ёваўн",
        "eng": "Yovon",
        "hye": "Յովոն",
        "hin": "योवोन",
        "ind": "Yovon",
        "kat": "იოვონი",
        "kaz": "Йовон",
        "kir": "Йовон",
        "msa": "Yovon",
        "por": "Yovon",
        "rus": "Йовон",
        "spa": "Yovon",
        "tgk": "Ёвон",
        "uzb": "Yovon",
        "ukr": "Йовон"
      }
    },
    {
      "name": "Proletar",
      "population": 16441,
      "translations": {
        "aze": "Proletar",
        "bel": "Пралятар",
        "eng": "Proletar",
        "hye": "Պրոլետար",
        "hin": "प्रोलेतार",
        "ind": "Proletar",
        "kat": "პროლეტარი",
        "kaz": "Пролетар",
        "kir": "Пролетар",
        "msa": "Proletar",
        "por": "Proletar",
        "rus": "Пролетар",
        "spa": "Proletar",
        "tgk": "Пролетар",
        "uzb": "Proletar",
        "ukr": "Пролетар"
      }
    },
    {
      "name": "Vakhsh",
      "population": 15215,
      "translations": {
        "aze": "Vaxş",
        "bel": "Вахш",
        "eng": "Vakhsh",
        "hye": "Վախշ",
        "hin": "वख्श",
        "ind": "Vakhsh",
        "kat": "ვახში",
        "kaz": "Вахш",
        "kir": "Вахш",
        "msa": "Vakhsh",
        "por": "Vakhsh",
        "rus": "Вахш",
        "spa": "Vakhsh",
        "tgk": "Вахш",
        "uzb": "Vaxsh",
        "ukr": "Вахш"
      }
    }
  ]
}
